{
  "backup_id": "unified_backup_20250629_104558_unified_",
  "session_id": "unified_1751193958455_c2c1f7d1",
  "timestamp": "2025-06-29T10:45:58.456863+00:00",
  "backup_type": "unified",
  "flags": {
    "corrupted": true
  },
  "session_data": {
    "_permanent": true,
    "session_id": "unified_1751193958455_c2c1f7d1"
  },
  "metadata": {
    "manager_stats": {
      "total_operations": 131,
      "successful_operations": 130,
      "failed_operations": 0,
      "timeouts": 0,
      "recoveries": 13,
      "cleanups": 4,
      "memory_optimizations": 2,
      "lock_contentions": 0
    },
    "session_registry": {},
    "memory_usage": {
      "usage_mb": 66.48,
      "threshold_mb": 500,
      "should_cleanup": false,
      "usage_percent": 13.3
    }
  }
}