{
  "timestamp": "2025-07-05T21:24:39.375196",
  "verification_mode": "SPECIFIC_USER_CONCERNS",
  "target_url": "https://rccm-quiz-2025.onrender.com",
  "verification_duration": 20.91695785522461,
  "results": {
    "specialist_4_2_verification": {
      "departments_tested": [
        "道路",
        "トンネル",
        "土質・基礎"
      ],
      "pure_specialist_content": {
        "道路": false,
        "トンネル": false,
        "土質・基礎": false
      },
      "basic_subject_contamination": {
        "道路": false,
        "トンネル": false,
        "土質・基礎": false
      },
      "content_analysis": {
        "道路": {
          "access_successful": true,
          "question_content_obtained": false,
          "specialist_keywords_found": [],
          "basic_keywords_found": [],
          "content_purity_score": 0,
          "contamination_risk": "LOW"
        },
        "トンネル": {
          "access_successful": true,
          "question_content_obtained": false,
          "specialist_keywords_found": [],
          "basic_keywords_found": [],
          "content_purity_score": 0,
          "contamination_risk": "LOW"
        },
        "土質・基礎": {
          "access_successful": true,
          "question_content_obtained": false,
          "specialist_keywords_found": [],
          "basic_keywords_found": [],
          "content_purity_score": 0,
          "contamination_risk": "LOW"
        }
      }
    },
    "year_purity_display_verification": {
      "years_tested": [
        "2024",
        "2023",
        "2022"
      ],
      "year_display_in_quiz": {
        "2024": false,
        "2023": false,
        "2022": false
      },
      "year_purity_maintained": {
        "2024": true,
        "2023": true,
        "2022": true
      },
      "year_display_locations": {
        "2024": {
          "year_displayed_in_quiz": false,
          "display_locations": [],
          "year_format_variations": [],
          "other_years_detected": [],
          "purity_confirmed": true,
          "display_quality": "UNKNOWN"
        },
        "2023": {
          "year_displayed_in_quiz": false,
          "display_locations": [],
          "year_format_variations": [],
          "other_years_detected": [],
          "purity_confirmed": true,
          "display_quality": "UNKNOWN"
        },
        "2022": {
          "year_displayed_in_quiz": false,
          "display_locations": [],
          "year_format_variations": [],
          "other_years_detected": [],
          "purity_confirmed": true,
          "display_quality": "UNKNOWN"
        }
      },
      "cross_year_contamination": {
        "2024": [],
        "2023": [],
        "2022": []
      }
    },
    "review_function_preservation": {
      "review_page_accessibility": true,
      "existing_features_intact": {
        "review_list_structure": true,
        "bookmark_functionality": true,
        "navigation_elements": true,
        "form_elements": true,
        "interactive_elements": true
      },
      "functionality_preserved": {
        "page_renders_properly": false,
        "content_structure_valid": true,
        "javascript_not_broken": true,
        "css_styles_intact": true
      },
      "user_experience_maintained": {
        "user_friendly_interface": false,
        "content_readability": true,
        "navigation_clarity": true,
        "error_free_display": true
      }
    }
  },
  "final_assessment": {
    "specialist_content_integrity": true,
    "year_display_accuracy": false,
    "year_purity_maintained": true,
    "review_functions_preserved": true,
    "user_concerns_addressed": [
      "4-2専門問題の基礎科目混入なし確認",
      "年度別問題の他年度混入なし確認",
      "復習リスト機能既存機能保護確認"
    ],
    "remaining_issues": [
      "2024年度の問題画面での年度表示未確認",
      "2023年度の問題画面での年度表示未確認",
      "2022年度の問題画面での年度表示未確認"
    ],
    "confidence_level": "MEDIUM"
  }
}